[{"major_title": "AS.101 Heritage and Values of the United States Air Force", "major_preq": "Prereq: None. Coreq: AS.111"}, {"major_title": "AS.102 Heritage and Values of the United States Air Force", "major_preq": "Prereq: AS.101 or permission of instructor; Coreq: AS.112"}, {"major_title": "AS.111 Leadership Laboratory", "major_preq": "Prereq: None. Coreq: AS.101"}, {"major_title": "AS.112 Leadership Laboratory", "major_preq": "Prereq: AS.111 or permission of instructor; Coreq: AS.102"}, {"major_title": "AS.201 Team and Leadership Fundamentals", "major_preq": "Prereq: AS.102 or permission of instructor; Coreq: AS.211"}, {"major_title": "AS.202 Team and Leadership Fundamentals", "major_preq": "Prereq: AS.201 or permission of instructor; Coreq: AS.212"}, {"major_title": "AS.211 Leadership Laboratory", "major_preq": "Prereq: AS.112 or permission of instructor; Coreq: AS.201"}, {"major_title": "AS.212 Leadership Laboratory", "major_preq": "Prereq: AS.211 or permission of instructor; Coreq: AS.202"}, {"major_title": "AS.301 Leading People and Effective Communication", "major_preq": "Prereq: AS.202 or permission of instructor; Coreq: AS.311"}, {"major_title": "AS.302 Leading People and Effective Communication", "major_preq": "Prereq: AS.301 or permission of instructor; Coreq: AS.312"}, {"major_title": "AS.311 Leadership Laboratory", "major_preq": "Prereq: AS.212 or permission of instructor; Coreq: AS.301"}, {"major_title": "AS.312 Leadership Laboratory", "major_preq": "Prereq: AS.311 or permission of instructor; Coreq: AS.302"}, {"major_title": "AS.401 National Security Affairs/Preparation for Active Duty", "major_preq": "Prereq: AS.302 or permission of instructor; Coreq: AS.411"}, {"major_title": "AS.402 National Security Affairs/Preparation for Active Duty", "major_preq": "Prereq: AS.401 or permission of instructor; Coreq: AS.412"}, {"major_title": "AS.411 Leadership Laboratory", "major_preq": "Prereq: AS.312 or permission of instructor; Coreq: AS.401"}, {"major_title": "AS.412 Leadership Laboratory", "major_preq": "Prereq: AS.411 or permission of instructor; Coreq: AS.402"}, {"major_title": "AS.511 Leadership Laboratory", "major_preq": "Prereq: AS.412 or permission of instructor"}, {"major_title": "AS.512 Leadership Laboratory", "major_preq": "Prereq: AS.511 or permission of instructor"}, {"major_title": "AS.811 Leadership Laboratory", "major_preq": "Prereq: AS.411 or permission of instructor"}, {"major_title": "AS.812 Leadership Laboratory", "major_preq": "Prereq: Permission of instructor"}]